aleat2/__init__.py
aleat2-0.0.1.dist-info/LICENSE
aleat2-0.0.1.dist-info/METADATA
aleat2-0.0.1.dist-info/WHEEL
aleat2-0.0.1.dist-info/top_level.txt
aleat2-0.0.1.dist-info/RECORD
